<?xml version="1.0" ?>
<world>
    <terrain size="12000 12000 510.0" spawnpos="3000 3000 100" heightmap="taintedplainsterrain.png" material="Terrain/TaintedPlains"/>
    <weathercycle name="Weirdsky"/>
    <freezetime time="0"/>
    <objectgroup mesh="acaciaTree" material="GUIMat/None(1)">
        <object pos="3527.0 9366.0 75.0" scale="2 2 2" rot="210 0 0"/>
        <object pos="3455.0 9204.0 75.0" scale="1 1 1" rot="20 0 0"/>
        <object pos="3383.0 9061.0 75.0" scale="1.2 1.2 1.2" rot="230 0 0"/>
        <object pos="3264.0 8913.0 75.0" scale="0.8 0.8 0.8" rot="40 0 0"/>
        <object pos="3186.0 8857.0 75.0" scale="1.6 1.6 1.6" rot="350 0 0"/>
        <object pos="3061.0 8730.0 75.0" scale="1.4 1.4 1.4" rot="60 0 0"/>
        <object pos="2949.0 8641.0 75.0" scale="1.2 1.2 1.2" rot="270 0 0"/>
        <object pos="2810.0 8556.0 75.0" scale="1.8 1.8 1.8" rot="80 0 0"/>
        <object pos="2692.0 8547.0 75.0" scale="1 1 1" rot="190 0 0"/>
        <object pos="2522.0 8523.0 75.0" scale="1.2 1.2 1.2" rot="230 0 0"/>
        <object pos="2353.0 8549.0 75.0" scale="0.8 0.8 0.8" rot="40 0 0"/>
        <object pos="2215.0 8648.0 75.0" scale="1.6 1.6 1.6" rot="350 0 0"/>
        <object pos="2055.0 8741.0 75.0" scale="1.4 1.4 1.4" rot="60 0 0"/>
        <object pos="1774.0 9011.0 75.0" scale="1.2 1.2 1.2" rot="270 0 0"/>
        <object pos="1679.0 9180.0 75.0" scale="1.8 1.8 1.8" rot="80 0 0"/>
        <object pos="5537.33 7069.49 110.0" scale="1.8 1.8 1.8" rot="80 0 0"/>
        <object pos="5684.66 6993.48 110.0" scale="1.1 1.1 1.1" rot="40 30 0"/>
        <object pos="5856.51 6843.13 100.0" scale="1.2 1.2 1.2" rot="20 20 10"/>
        <object pos="5974.3 6648.85 90.0" scale="1.4 1.4 1.4" rot="10 10 30"/>
        <object pos="6013.13 6420.77 90.0" scale="1.1 1.1 1.1" rot="180 5 20"/>
        <object pos="5974.79 6207.54 90.0" scale="1.8 1.8 1.8" rot="280 10 0"/>
        <object pos="5841.19 5996.79 90.0" scale="1.5 1.5 1.5" rot="60 0 20"/>
        <object pos="5682.96 5847.47 100.0" scale="1.3 1.3 1.3" rot="120 20 10"/>
        <object pos="5462.18 5790.64 100.0" scale="1.2 1.2 1.2" rot="140 30 0"/>
        <object pos="5205.43 5816.02 100.0" scale="1.6 1.6 1.6" rot="160 0 4"/>
        <object pos="5004.99 5910.77 100.0" scale="1.7 1.7 1.7" rot="170 11 7"/>
        <object pos="4819.15 6144.75 100.0" scale="1.8 1.8 1.8" rot="0 0 0"/>
        <object pos="4545.73 3850.24 150.0" scale="1.7 1.7 1.7" rot="170 11 7"/>
        <object pos="5158.84 2698.370000000001 160.0" scale="1.7 1.7 1.7" rot="70 15 17"/>
        <object pos="6012.38 2672.540000000001 130.0" scale="1.7 1.7 1.7" rot="10 1 27"/>
        <object pos="6611.38 2029.8999999999996 120.0" scale="1.7 1.7 1.7" rot="170 0 37"/>
        <object pos="7366.85 1464.3999999999996 130.0" scale="1.7 1.7 1.7" rot="120 21 47"/>
        <object pos="8183.94 2619.7800000000007 120.0" scale="1.7 1.7 1.7" rot="130 31 7"/>
        <object pos="7791.58 3613.92 120.0" scale="1.7 1.7 1.7" rot="140 5 17"/>
        <object pos="8070.64 5140.84 160.0" scale="1.7 1.7 1.7" rot="150 7 27"/>
        <object pos="8592.15 5963.46 140.0" scale="1.7 1.7 1.7" rot="160 40 7"/>
        <object pos="8677.45 7253.37 130.0" scale="1.7 1.7 1.7" rot="170 11 37"/>
        <object pos="9180.51 8155.030000000001 150.0" scale="1.7 1.7 1.7" rot="70 1 7"/>
        <object pos="9764.41 8679.46 140.0" scale="1.7 1.7 1.7" rot="10 1 17"/>
        <object pos="9465.39 9375.8 130.0" scale="1.7 1.7 1.7" rot="0 11 7"/>
        <object pos="8871.8 10481.53 120.0" scale="1.7 1.7 1.7" rot="40 31 17"/>
        <object pos="7725.93 10620.1 120.0" scale="1.7 1.7 1.7" rot="170 11 7"/>
        <object pos="6613.99 10540.57 120.0" scale="1.7 1.7 1.7" rot="270 21 27"/>
        <object pos="5718.45 9693.06 140.0" scale="1.7 1.7 1.7" rot="230 1 37"/>
        <object pos="3614.87 10766.81 100.0" scale="1.7 1.7 1.7" rot="250 1 7"/>
        <object pos="2917.08 4280.44 110.0" scale="1.3 1.3 1.3" rot="120 21 47"/>
        <object pos="2377.0 3497.120000000001 140.0" scale="1.3 1.3 1.3" rot="0 0 0"/>
        <object pos="2492.09 2385.1499999999996 150.0" scale="1.3 1.3 1.3" rot="170 0 37"/>
        <object pos="2389.03 1588.1000000000004 150.0" scale="1.3 1.3 1.3" rot="140 5 17"/>
        <object pos="1612.95 911.3999999999996 170.0" scale="1.3 1.3 1.3" rot="170 11 37"/>
        <object pos="1005.49 2639.9699999999993 160.0" scale="1.3 1.3 1.3" rot="280 10 0"/>
        <object pos="1501.81 3594.99 140.0" scale="1.3 1.3 1.3" rot="80 0 0"/>
        <object pos="2044.96 4699.53 100.0" scale="1.3 1.3 1.3" rot="230 1 37"/>
        <object pos="2221.79 5622.2 110.0" scale="1.3 1.3 1.3" rot="120 21 47"/>
    </objectgroup>
    <objectgroup mesh="pumpkin" material="">
        <object pos="4595.0 7033.0 262.0" scale="13 13 13" rot="0 0 0"/>
        <object pos="7376.79 2550.08 105.651" scale="1.3 1.3 1.3" rot="0 0 0"/>
        <object pos="7280.85 2450.1900000000005 104.294" scale="1.4 1.4 1.4" rot="10 10 0"/>
        <object pos="7393.1 2470.3199999999997 105.147" scale="1.6 1.6 1.6" rot="20 5 55"/>
        <object pos="7481.22 2547.8899999999994 107.059" scale="1.3 1.3 1.3" rot="30 0 10"/>
        <object pos="7394.4 2734.1000000000004 108.235" scale="1.4 1.4 1.4" rot="40 0 30"/>
        <object pos="7295.66 2728.76 107.411" scale="1.4 1.4 1.4" rot="50 0 0"/>
        <object pos="7198.34 2687.7199999999993 105.533" scale="1.6 1.6 1.6" rot="60 2 5"/>
        <object pos="7158.0 2548.7700000000004 103.529" scale="1.3 1.3 1.3" rot="70 20 10"/>
        <object pos="7159.05 2415.3899999999994 104.178" scale="1.4 1.4 1.4" rot="80 0 -50"/>
        <object pos="7178.44 2304.290000000001 105.454" scale="1.3 1.3 1.3" rot="90 0 0"/>
        <object pos="7265.3 2289.540000000001 105.882" scale="1.3 1.3 1.3" rot="100 -20 0"/>
        <object pos="7370.79 2325.5699999999997 105.023" scale="1.6 1.6 1.6" rot="110 0 0"/>
        <object pos="7462.0 2400.3199999999997 105.882" scale="1.3 1.3 1.3" rot="120 0 0"/>
        <object pos="7519.36 2506.5 107.059" scale="1.4 1.4 1.4" rot="130 0 0"/>
        <object pos="7512.15 2620.0300000000007 108.235" scale="1.3 1.3 1.3" rot="140 -10 0"/>
        <object pos="7496.1 2720.17 109.443" scale="1.3 1.3 1.3" rot="150 0 0"/>
        <object pos="7432.2 2823.76 111.109" scale="1.3 1.3 1.3" rot="160 0 -50"/>
        <object pos="7322.86 2839.1900000000005 109.575" scale="1.4 1.4 1.4" rot="170 0 50"/>
        <object pos="7235.09 2831.370000000001 108.235" scale="1.3 1.3 1.3" rot="180 20 10"/>
        <object pos="7101.56 2744.8600000000006 104.865" scale="1.4 1.4 1.4" rot="190 -10 -20"/>
        <object pos="7042.37 2604.1399999999994 103.529" scale="1.4 1.4 1.4" rot="200 5 -10"/>
        <object pos="7048.97 2465.24 104.455" scale="1.6 1.6 1.6" rot="210 0 0"/>
        <object pos="7056.25 2351.08 105.812" scale="1.3 1.3 1.3" rot="220 -5 5"/>
        <object pos="7076.27 2225.879999999999 108.235" scale="1.4 1.4 1.4" rot="230 2 1"/>
        <object pos="7100.15 2115.2299999999996 110.654" scale="1.3 1.3 1.3" rot="240 0 0"/>
        <object pos="7178.79 2100.92 110.289" scale="1.6 1.6 1.6" rot="250 12 4"/>
        <object pos="7296.82 2072.8899999999994 110.042" scale="1.4 1.4 1.4" rot="260 0 0"/>
        <object pos="7397.34 2053.3600000000006 109.868" scale="1.3 1.3 1.3" rot="270 -14 20"/>
        <object pos="7476.5 2073.5599999999995 110.069" scale="1.3 1.3 1.3" rot="280 20 -14"/>
        <object pos="7578.69 2109.59 110.588" scale="1.4 1.4 1.4" rot="290 0 0"/>
        <object pos="7719.54 2218.58 111.765" scale="1.6 1.6 1.6" rot="300 40 -40"/>
        <object pos="7484.13 2224.209999999999 107.177" scale="5 5 5" rot="310 0 0"/>
    </objectgroup>
    <objectgroup mesh="candles" material="">
        <object pos="4595.0 7033.0 262.0" scale="3 3 3" rot="0 0 0"/>
        <object pos="4592.18 6949.5 258.0" scale="1.2 1.2 1.2" rot="0 0 0"/>
        <object pos="4625.82 6966.93 258.0" scale="1.3 1.3 1.3" rot="90 0 0"/>
        <object pos="4654.38 7003.61 258.0" scale="1.2 1.2 1.2" rot="30 0 0"/>
        <object pos="4656.34 7056.58 260.0" scale="1.4 1.4 1.4" rot="160 0 0"/>
        <object pos="4618.25 7100.75 260.0" scale="1.5 1.5 1.5" rot="60 0 0"/>
        <object pos="4578.82 7094.62 261.0" scale="1.4 1.4 1.4" rot="190 0 0"/>
        <object pos="4540.5 7068.49 261.0" scale="1.2 1.2 1.2" rot="40 0 0"/>
        <object pos="4531.42 7028.61 262.0" scale="1.3 1.3 1.3" rot="200 0 0"/>
        <object pos="4541.43 6972.44 262.0" scale="1.2 1.2 1.2" rot="270 0 0"/>
        <object pos="9643.93 4326.05 127.059" scale="1.3 1.3 1.3" rot="0 0 0"/>
        <object pos="9566.04 4341.48 124.884" scale="1.3 1.3 1.3" rot="10 0 0"/>
        <object pos="9471.28 4353.18 122.48" scale="1.3 1.3 1.3" rot="20 0 0"/>
        <object pos="9362.08 4366.04 121.176" scale="1.3 1.3 1.3" rot="30 0 0"/>
        <object pos="9349.77 4403.06 121.176" scale="1.3 1.3 1.3" rot="40 0 0"/>
        <object pos="9324.25 4481.23 121.176" scale="1.3 1.3 1.3" rot="50 0 0"/>
        <object pos="9364.8 4559.52 122.988" scale="1.3 1.3 1.3" rot="60 0 0"/>
        <object pos="9483.56 4547.72 124.273" scale="1.3 1.3 1.3" rot="70 0 0"/>
        <object pos="9516.85 4488.34 124.706" scale="1.3 1.3 1.3" rot="80 0 0"/>
        <object pos="9588.07 4445.51 125.882" scale="1.3 1.3 1.3" rot="90 0 0"/>
        <object pos="9289.19 4293.08 120.0" scale="1.3 1.3 1.3" rot="100 0 0"/>
        <object pos="9312.66 4217.7 120.0" scale="1.3 1.3 1.3" rot="110 0 0"/>
        <object pos="9408.2 4194.74 121.667" scale="1.3 1.3 1.3" rot="120 0 0"/>
        <object pos="9506.25 4386.13 123.529" scale="1.5 1.5 1.5" rot="130 0 0"/>
        <object pos="9513.51 4398.78 123.529" scale="1.6 1.6 1.6" rot="140 0 0"/>
        <object pos="7942.81 9664.78 114.74" scale="1.3 1.3 1.3" rot="0 0 0"/>
        <object pos="7969.42 9693.03 114.118" scale="1.3 1.3 1.3" rot="30 0 0"/>
        <object pos="8009.02 9692.64 114.313" scale="1.4 1.4 1.4" rot="60 0 0"/>
        <object pos="8017.25 9673.96 115.294" scale="1.5 1.5 1.5" rot="90 0 0"/>
        <object pos="8029.76 9642.96 115.494" scale="1.3 1.3 1.3" rot="120 0 0"/>
        <object pos="7998.96 9620.58 115.908" scale="1.4 1.4 1.4" rot="150 0 0"/>
        <object pos="7972.61 9635.32 115.294" scale="1.3 1.3 1.3" rot="180 0 0"/>
    </objectgroup>
    <objectgroup mesh="grave" material="">
        <object pos="9670.62 4615.14 128.235" scale="1.2 1.2 1.2" rot="0 10 5"/>
        <object pos="9611.41 4613.7 127.059" scale="1.2 1.2 1.2" rot="10 0 15"/>
        <object pos="9624.96 4556.7 127.059" scale="1.3 1.3 1.3" rot="20 20 25"/>
        <object pos="9650.17 4486.04 127.059" scale="1 1 1" rot="0 10 5"/>
        <object pos="9712.07 4533.06 128.684" scale="1.2 1.2 1.2" rot="40 20 15"/>
        <object pos="9566.51 4441.03 124.907" scale="1.3 1.3 1.3" rot="50 10 5"/>
        <object pos="9504.4 4491.44 124.143" scale="1.2 1.2 1.2" rot="60 10 25"/>
        <object pos="9467.6 4552.24 123.801" scale="1.5 1.5 1.5" rot="70 10 5"/>
        <object pos="9362.46 4571.38 122.9" scale="1.2 1.2 1.2" rot="80 10 15"/>
        <object pos="9360.41 4516.61 122.353" scale="1.3 1.3 1.3" rot="90 0 15"/>
        <object pos="9362.65 4461.88 121.733" scale="1.3 1.3 1.3" rot="100 10 5"/>
        <object pos="9389.65 4386.38 121.176" scale="1.2 1.2 1.2" rot="110 10 25"/>
        <object pos="9420.04 4326.23 122.261" scale="1.2 1.2 1.2" rot="120 0 25"/>
        <object pos="9484.94 4295.8 123.166" scale="1.3 1.3 1.3" rot="130 10 5"/>
        <object pos="9535.76 4277.15 124.54" scale="1.7 1.7 1.7" rot="140 0 5"/>
        <object pos="9528.86 4222.87 124.706" scale="1.2 1.2 1.2" rot="150 20 15"/>
        <object pos="9474.4 4228.23 123.337" scale="1.2 1.2 1.2" rot="160 0 5"/>
        <object pos="9412.96 4244.49 121.906" scale="1.3 1.3 1.3" rot="170 0 5"/>
        <object pos="9377.06 4290.83 121.176" scale="1.2 1.2 1.2" rot="180 10 15"/>
        <object pos="9319.74 4334.74 120.0" scale="1.3 1.3 1.3" rot="190 10 5"/>
        <object pos="9280.7 4357.95 120.0" scale="1 1 1" rot="200 10 25"/>
        <object pos="9274.16 4306.45 120.0" scale="1.2 1.2 1.2" rot="210 10 5"/>
        <object pos="9313.7 4236.28 120.0" scale="1.3 1.3 1.3" rot="220 20 15"/>
        <object pos="9350.93 4188.21 120.0" scale="1.3 1.3 1.3" rot="230 30 5"/>
        <object pos="9500.93 4396.21 120.0" scale="3 3 3" rot="240 1 2"/>
        <object pos="7986.66 9664.36 114.887" scale="3 3 3" rot="0 0 0"/>
    </objectgroup>
    <waterplane pos="5384.0 6340.0 90.0" scale="3 3" material="Terrain/bloodWater" sound="" issolid="false"/>
    <gate material="GateMatShriekingHill" pos="2371.0 4475.0 117.0" destmap="Shrieking Hill" destvec="941.0 8303.0"/>
</world>
